Doxyfile
LICENSE.txt
distribute_setup.py
setup.cfg
setup.py
setup_hooks.py
doc/History
libf2c/Notice
libf2c/abort_.c
libf2c/arith.h
libf2c/arithchk.c
libf2c/backspac.c
libf2c/c_abs.c
libf2c/c_cos.c
libf2c/c_div.c
libf2c/c_exp.c
libf2c/c_log.c
libf2c/c_sin.c
libf2c/c_sqrt.c
libf2c/cabs.c
libf2c/close.c
libf2c/common_files.dat
libf2c/d_abs.c
libf2c/d_acos.c
libf2c/d_asin.c
libf2c/d_atan.c
libf2c/d_atn2.c
libf2c/d_cnjg.c
libf2c/d_cos.c
libf2c/d_cosh.c
libf2c/d_dim.c
libf2c/d_exp.c
libf2c/d_imag.c
libf2c/d_int.c
libf2c/d_lg10.c
libf2c/d_log.c
libf2c/d_mod.c
libf2c/d_nint.c
libf2c/d_prod.c
libf2c/d_sign.c
libf2c/d_sin.c
libf2c/d_sinh.c
libf2c/d_sqrt.c
libf2c/d_tan.c
libf2c/d_tanh.c
libf2c/derf_.c
libf2c/derfc_.c
libf2c/dfe.c
libf2c/dolio.c
libf2c/dtime_.c
libf2c/due.c
libf2c/ef1asc_.c
libf2c/ef1cmc_.c
libf2c/endfile.c
libf2c/erf_.c
libf2c/erfc_.c
libf2c/err.c
libf2c/etime_.c
libf2c/exit_.c
libf2c/f2c.h
libf2c/f77_aloc.c
libf2c/f77vers.c
libf2c/fio.h
libf2c/fmt.c
libf2c/fmt.h
libf2c/fmtlib.c
libf2c/fp.h
libf2c/ftell64_.c
libf2c/ftell_.c
libf2c/getarg_.c
libf2c/getenv_.c
libf2c/h_abs.c
libf2c/h_dim.c
libf2c/h_dnnt.c
libf2c/h_indx.c
libf2c/h_len.c
libf2c/h_mod.c
libf2c/h_nint.c
libf2c/h_sign.c
libf2c/hl_ge.c
libf2c/hl_gt.c
libf2c/hl_le.c
libf2c/hl_lt.c
libf2c/i77vers.c
libf2c/i_abs.c
libf2c/i_dim.c
libf2c/i_dnnt.c
libf2c/i_indx.c
libf2c/i_len.c
libf2c/i_mod.c
libf2c/i_nint.c
libf2c/i_sign.c
libf2c/iargc_.c
libf2c/iio.c
libf2c/ilnw.c
libf2c/inquire.c
libf2c/l_ge.c
libf2c/l_gt.c
libf2c/l_le.c
libf2c/l_lt.c
libf2c/lbitbits.c
libf2c/lbitshft.c
libf2c/lio.h
libf2c/lread.c
libf2c/lwrite.c
libf2c/main.c
libf2c/open.c
libf2c/pow_ci.c
libf2c/pow_dd.c
libf2c/pow_di.c
libf2c/pow_hh.c
libf2c/pow_ii.c
libf2c/pow_qq.c
libf2c/pow_ri.c
libf2c/pow_zi.c
libf2c/pow_zz.c
libf2c/qbitbits.c
libf2c/qbitshft.c
libf2c/r_abs.c
libf2c/r_acos.c
libf2c/r_asin.c
libf2c/r_atan.c
libf2c/r_atn2.c
libf2c/r_cnjg.c
libf2c/r_cos.c
libf2c/r_cosh.c
libf2c/r_dim.c
libf2c/r_exp.c
libf2c/r_imag.c
libf2c/r_int.c
pydrizzle.egg-info/PKG-INFO
pydrizzle.egg-info/SOURCES.txt
pydrizzle.egg-info/dependency_links.txt
pydrizzle.egg-info/not-zip-safe
pydrizzle.egg-info/requires.txt
pydrizzle.egg-info/top_level.txt
